cosmian_lib_anonymization/__init__.py
cosmian_lib_anonymization/anonymization.py
cosmian_lib_anonymization/anonymize_dataset.py
cosmian_lib_anonymization-0.1.2.dist-info/METADATA
cosmian_lib_anonymization-0.1.2.dist-info/WHEEL
cosmian_lib_anonymization-0.1.2.dist-info/top_level.txt
cosmian_lib_anonymization-0.1.2.dist-info/RECORD
