Metadata-Version: 2.1
Name: cosmian-lib-anonymization
Version: 0.1.2
Summary: Python library to anonymize csv datasets
Home-page: https://cosmian.com
Author: Cosmian Tech
Author-email: tech@cosmian.com
License: MIT
Keywords: python,cosmian,anonymization
Classifier: Programming Language :: Python :: 3
Classifier: License :: OSI Approved :: MIT License
Classifier: Operating System :: OS Independent
Requires-Dist: cryptography
Requires-Dist: numpy
Requires-Dist: pandas
